{
    "id": "8f2bb20361d41620f8385525cc5329e8",
    "name": "Elastic Email SMTP API",
    "description": null,
    "auth": null,
    "events": null,
    "variables": [],
    "order": [],
    "folders_order": [],
    "folders": [],
    "requests": [
        {
            "id": "07ee217998016211774cabf81e51f5b1",
            "name": "Upload Attachment",
            "url": "httpapi.elasticemail.com\/attachments\/upload\/",
            "description": "The upload attachment command is used to upload an attachment for sending.  ",
            "data": [],
            "dataMode": "raw",
            "headerData": null,
            "method": "get",
            "pathVariableData": [],
            "queryParams": [
                {
                    "key": "api_key",
                    "description": "your api key",
                    "value": "",
                    "equals": true,
                    "enabled": true
                },
                {
                    "key": "file",
                    "description": "The file name being uploaded",
                    "value": "",
                    "equals": true,
                    "enabled": true
                },
                {
                    "key": "username",
                    "description": "username",
                    "value": "",
                    "equals": true,
                    "enabled": true
                }
            ],
            "auth": null,
            "events": null,
            "folder": null,
            "protocolProfileBehavior": {
                "disableBodyPruning": true
            },
            "responses": [],
            "currentHelper": null,
            "helperAttributes": null,
            "collectionId": "8f2bb20361d41620f8385525cc5329e8",
            "rawModeData": ""
        },
        {
            "id": "f381f7e80519fc63154908fedff18d48",
            "name": "Add Existing Subscriber To List",
            "url": "httpapi.elasticemail.com\/lists\/add-contact",
            "description": "Add Existing Subscriber To List",
            "data": [],
            "dataMode": "raw",
            "headerData": null,
            "method": "get",
            "pathVariableData": [],
            "queryParams": [
                {
                    "key": "api_key",
                    "description": "your api key",
                    "value": "",
                    "equals": true,
                    "enabled": true
                },
                {
                    "key": "listname",
                    "description": "name of list you wish to add subscriber to (separate by semi-colon to add to multiple lists)",
                    "value": "",
                    "equals": true,
                    "enabled": true
                },
                {
                    "key": "username",
                    "description": "username",
                    "value": "",
                    "equals": true,
                    "enabled": true
                }
            ],
            "auth": null,
            "events": null,
            "folder": null,
            "protocolProfileBehavior": {
                "disableBodyPruning": true
            },
            "responses": [],
            "currentHelper": null,
            "helperAttributes": null,
            "collectionId": "8f2bb20361d41620f8385525cc5329e8",
            "rawModeData": ""
        },
        {
            "id": "c68686637a936b7a0459c54195ac29e0",
            "name": "Create New Subscriber",
            "url": "httpapi.elasticemail.com\/lists\/create-contact",
            "description": "Create New Subscriber",
            "data": [],
            "dataMode": "raw",
            "headerData": null,
            "method": "get",
            "pathVariableData": [],
            "queryParams": [
                {
                    "key": "api_key",
                    "description": "your api key",
                    "value": "",
                    "equals": true,
                    "enabled": true
                },
                {
                    "key": "birthdate",
                    "description": "date of birth of the subscriber",
                    "value": "",
                    "equals": true,
                    "enabled": true
                },
                {
                    "key": "city",
                    "description": "city of the subscriber",
                    "value": "",
                    "equals": true,
                    "enabled": true
                },
                {
                    "key": "country",
                    "description": "country of the subscriber",
                    "value": "",
                    "equals": true,
                    "enabled": true
                },
                {
                    "key": "email",
                    "description": "email address of subscriber\/recipient",
                    "value": "",
                    "equals": true,
                    "enabled": true
                },
                {
                    "key": "firstname",
                    "description": "first name of the subscriber",
                    "value": "",
                    "equals": true,
                    "enabled": true
                },
                {
                    "key": "gender",
                    "description": "male or female",
                    "value": "",
                    "equals": true,
                    "enabled": true
                },
                {
                    "key": "lastname",
                    "description": " last name of the subscriber",
                    "value": "",
                    "equals": true,
                    "enabled": true
                },
                {
                    "key": "listname",
                    "description": "name of list you wish to add subscriber to (separate by semi-colon to add to multiple lists)",
                    "value": "",
                    "equals": true,
                    "enabled": true
                },
                {
                    "key": "organizationname",
                    "description": "organization name the subscriber works for",
                    "value": "",
                    "equals": true,
                    "enabled": true
                },
                {
                    "key": "phone",
                    "description": "phone number for the subscriber",
                    "value": "",
                    "equals": true,
                    "enabled": true
                },
                {
                    "key": "postalcode",
                    "description": "the zip or postal code of the subscriber",
                    "value": "",
                    "equals": true,
                    "enabled": true
                },
                {
                    "key": "state",
                    "description": "the state or province for the subscriber",
                    "value": "",
                    "equals": true,
                    "enabled": true
                },
                {
                    "key": "the zip or postal code of the subscriber",
                    "description": "Your user name.",
                    "value": "",
                    "equals": true,
                    "enabled": true
                },
                {
                    "key": "title",
                    "description": "the title for the subscriber (Mr., Mrs, Miss, etc)",
                    "value": "",
                    "equals": true,
                    "enabled": true
                }
            ],
            "auth": null,
            "events": null,
            "folder": null,
            "protocolProfileBehavior": {
                "disableBodyPruning": true
            },
            "responses": [],
            "currentHelper": null,
            "helperAttributes": null,
            "collectionId": "8f2bb20361d41620f8385525cc5329e8",
            "rawModeData": ""
        },
        {
            "id": "e5b6c0f2f5900c31d8505e9d597b00d0",
            "name": "Create New List",
            "url": "httpapi.elasticemail.com\/lists\/create-lists",
            "description": "Create New List",
            "data": [],
            "dataMode": "raw",
            "headerData": null,
            "method": "get",
            "pathVariableData": [],
            "queryParams": [
                {
                    "key": "api_key",
                    "description": "your api key",
                    "value": "",
                    "equals": true,
                    "enabled": true
                },
                {
                    "key": "listname",
                    "description": "name of list you wish to add subscriber to (separate by semi-colon to add to multiple lists)",
                    "value": "",
                    "equals": true,
                    "enabled": true
                },
                {
                    "key": "username",
                    "description": "username",
                    "value": "",
                    "equals": true,
                    "enabled": true
                }
            ],
            "auth": null,
            "events": null,
            "folder": null,
            "protocolProfileBehavior": {
                "disableBodyPruning": true
            },
            "responses": [],
            "currentHelper": null,
            "helperAttributes": null,
            "collectionId": "8f2bb20361d41620f8385525cc5329e8",
            "rawModeData": ""
        },
        {
            "id": "2eda22ee668b790ef9f4efd02b3c632f",
            "name": "Delete Existing List",
            "url": "httpapi.elasticemail.com\/lists\/delete",
            "description": "Delete Existing List",
            "data": [],
            "dataMode": "raw",
            "headerData": null,
            "method": "get",
            "pathVariableData": [],
            "queryParams": [
                {
                    "key": "api_key",
                    "description": "your api key",
                    "value": "",
                    "equals": true,
                    "enabled": true
                },
                {
                    "key": "listname",
                    "description": "name of list you wish to add subscriber to (separate by semi-colon to add to multiple lists)",
                    "value": "",
                    "equals": true,
                    "enabled": true
                },
                {
                    "key": "username",
                    "description": "username",
                    "value": "",
                    "equals": true,
                    "enabled": true
                }
            ],
            "auth": null,
            "events": null,
            "folder": null,
            "protocolProfileBehavior": {
                "disableBodyPruning": true
            },
            "responses": [],
            "currentHelper": null,
            "helperAttributes": null,
            "collectionId": "8f2bb20361d41620f8385525cc5329e8",
            "rawModeData": ""
        },
        {
            "id": "102e78abffabab05aff82bd7e34a3107",
            "name": "Delete Existing Subscriber",
            "url": "httpapi.elasticemail.com\/lists\/delete-contact",
            "description": "Delete Existing Subscriber",
            "data": [],
            "dataMode": "raw",
            "headerData": null,
            "method": "get",
            "pathVariableData": [],
            "queryParams": [
                {
                    "key": "api_key",
                    "description": "your api key",
                    "value": "",
                    "equals": true,
                    "enabled": true
                },
                {
                    "key": "email",
                    "description": "email address of subscriber\/recipient",
                    "value": "",
                    "equals": true,
                    "enabled": true
                },
                {
                    "key": "username",
                    "description": "username",
                    "value": "",
                    "equals": true,
                    "enabled": true
                }
            ],
            "auth": null,
            "events": null,
            "folder": null,
            "protocolProfileBehavior": {
                "disableBodyPruning": true
            },
            "responses": [],
            "currentHelper": null,
            "helperAttributes": null,
            "collectionId": "8f2bb20361d41620f8385525cc5329e8",
            "rawModeData": ""
        },
        {
            "id": "b63d15b4f507f7aaf7548c9cee7b9655",
            "name": "Remove Existing Subscriber From List",
            "url": "httpapi.elasticemail.com\/lists\/remove-contact",
            "description": "Remove Existing Subscriber From List",
            "data": [],
            "dataMode": "raw",
            "headerData": null,
            "method": "get",
            "pathVariableData": [],
            "queryParams": [
                {
                    "key": "api_key",
                    "description": "your api key",
                    "value": "",
                    "equals": true,
                    "enabled": true
                },
                {
                    "key": "listname",
                    "description": "name of list you wish to add subscriber to (separate by semi-colon to add to multiple lists)",
                    "value": "",
                    "equals": true,
                    "enabled": true
                },
                {
                    "key": "username",
                    "description": "username",
                    "value": "",
                    "equals": true,
                    "enabled": true
                }
            ],
            "auth": null,
            "events": null,
            "folder": null,
            "protocolProfileBehavior": {
                "disableBodyPruning": true
            },
            "responses": [],
            "currentHelper": null,
            "helperAttributes": null,
            "collectionId": "8f2bb20361d41620f8385525cc5329e8",
            "rawModeData": ""
        },
        {
            "id": "efb3c76723c5bbc3d5ecdb5870de3b70",
            "name": "Create Multiple Subscriber From CSV File",
            "url": "httpapi.elasticemail.com\/lists\/upload-contacts",
            "description": "Create Multiple Subscriber From CSV File",
            "data": [],
            "dataMode": "raw",
            "headerData": null,
            "method": "get",
            "pathVariableData": [],
            "queryParams": [
                {
                    "key": "api_key",
                    "description": "your api key",
                    "value": "",
                    "equals": true,
                    "enabled": true
                },
                {
                    "key": "birthdate",
                    "description": "date of birth of the subscriber",
                    "value": "",
                    "equals": true,
                    "enabled": true
                },
                {
                    "key": "city",
                    "description": "city of the subscriber",
                    "value": "",
                    "equals": true,
                    "enabled": true
                },
                {
                    "key": "country",
                    "description": "country of the subscriber",
                    "value": "",
                    "equals": true,
                    "enabled": true
                },
                {
                    "key": "email",
                    "description": "email address of subscriber\/recipient",
                    "value": "",
                    "equals": true,
                    "enabled": true
                },
                {
                    "key": "firstname",
                    "description": "first name of the subscriber",
                    "value": "",
                    "equals": true,
                    "enabled": true
                },
                {
                    "key": "gender",
                    "description": "male or female",
                    "value": "",
                    "equals": true,
                    "enabled": true
                },
                {
                    "key": "lastname",
                    "description": " last name of the subscriber",
                    "value": "",
                    "equals": true,
                    "enabled": true
                },
                {
                    "key": "listname",
                    "description": "name of list you wish to add subscriber to (separate by semi-colon to add to multiple lists)",
                    "value": "",
                    "equals": true,
                    "enabled": true
                },
                {
                    "key": "organizationname",
                    "description": "organization name the subscriber works for",
                    "value": "",
                    "equals": true,
                    "enabled": true
                },
                {
                    "key": "phone",
                    "description": "phone number for the subscriber",
                    "value": "",
                    "equals": true,
                    "enabled": true
                },
                {
                    "key": "postalcode",
                    "description": "the zip or postal code of the subscriber",
                    "value": "",
                    "equals": true,
                    "enabled": true
                },
                {
                    "key": "state",
                    "description": "the state or province for the subscriber",
                    "value": "",
                    "equals": true,
                    "enabled": true
                },
                {
                    "key": "title",
                    "description": "the title for the subscriber (Mr., Mrs, Miss, etc)",
                    "value": "",
                    "equals": true,
                    "enabled": true
                },
                {
                    "key": "username",
                    "description": "username",
                    "value": "",
                    "equals": true,
                    "enabled": true
                }
            ],
            "auth": null,
            "events": null,
            "folder": null,
            "protocolProfileBehavior": {
                "disableBodyPruning": true
            },
            "responses": [],
            "currentHelper": null,
            "helperAttributes": null,
            "collectionId": "8f2bb20361d41620f8385525cc5329e8",
            "rawModeData": ""
        },
        {
            "id": "7fb67b74c8132523d2bd08cfc40f7a06",
            "name": "Account Details",
            "url": "httpapi.elasticemail.com\/mailer\/account-details",
            "description": "The Account Details command is used to determine how much credit you have left.  ",
            "data": [],
            "dataMode": "raw",
            "headerData": null,
            "method": "get",
            "pathVariableData": [],
            "queryParams": [
                {
                    "key": "api_key",
                    "description": "your api key",
                    "value": "",
                    "equals": true,
                    "enabled": true
                },
                {
                    "key": "username",
                    "description": "username",
                    "value": "",
                    "equals": true,
                    "enabled": true
                }
            ],
            "auth": null,
            "events": null,
            "folder": null,
            "protocolProfileBehavior": {
                "disableBodyPruning": true
            },
            "responses": [],
            "currentHelper": null,
            "helperAttributes": null,
            "collectionId": "8f2bb20361d41620f8385525cc5329e8",
            "rawModeData": ""
        },
        {
            "id": "73d73fdf052a1cf8c4612e8d7b129424",
            "name": "Deleting Channel",
            "url": "httpapi.elasticemail.com\/mailer\/channel\/delete",
            "description": "Deleting Channel",
            "data": [],
            "dataMode": "raw",
            "headerData": null,
            "method": "get",
            "pathVariableData": [],
            "queryParams": [
                {
                    "key": "api_key",
                    "description": "your api key",
                    "value": "",
                    "equals": true,
                    "enabled": true
                },
                {
                    "key": "format",
                    "description": "csv or xml",
                    "value": "",
                    "equals": true,
                    "enabled": true
                },
                {
                    "key": "name",
                    "description": "channel name to delete",
                    "value": "",
                    "equals": true,
                    "enabled": true
                },
                {
                    "key": "username",
                    "description": "username",
                    "value": "",
                    "equals": true,
                    "enabled": true
                }
            ],
            "auth": null,
            "events": null,
            "folder": null,
            "protocolProfileBehavior": {
                "disableBodyPruning": true
            },
            "responses": [],
            "currentHelper": null,
            "helperAttributes": null,
            "collectionId": "8f2bb20361d41620f8385525cc5329e8",
            "rawModeData": ""
        },
        {
            "id": "966def2e4ccc08985698da8d3f0b3087",
            "name": "Listing of Active Channels",
            "url": "httpapi.elasticemail.com\/mailer\/channel\/list",
            "description": "Listing of Active Channels",
            "data": [],
            "dataMode": "raw",
            "headerData": null,
            "method": "get",
            "pathVariableData": [],
            "queryParams": [
                {
                    "key": "api_key",
                    "description": "your api key",
                    "value": "",
                    "equals": true,
                    "enabled": true
                },
                {
                    "key": "format",
                    "description": "csv or xml",
                    "value": "",
                    "equals": true,
                    "enabled": true
                },
                {
                    "key": "username",
                    "description": "username",
                    "value": "",
                    "equals": true,
                    "enabled": true
                }
            ],
            "auth": null,
            "events": null,
            "folder": null,
            "protocolProfileBehavior": {
                "disableBodyPruning": true
            },
            "responses": [],
            "currentHelper": null,
            "helperAttributes": null,
            "collectionId": "8f2bb20361d41620f8385525cc5329e8",
            "rawModeData": ""
        },
        {
            "id": "46572db21fb28d8259b70c505de213e4",
            "name": "Bounced",
            "url": "httpapi.elasticemail.com\/mailer\/list\/bounced",
            "description": "This api will return you the list of email addresses which are currently in your block list. ",
            "data": [],
            "dataMode": "raw",
            "headerData": null,
            "method": "get",
            "pathVariableData": [],
            "queryParams": [
                {
                    "key": "api_key",
                    "description": "your api key",
                    "value": "",
                    "equals": true,
                    "enabled": true
                },
                {
                    "key": "username",
                    "description": "username",
                    "value": "",
                    "equals": true,
                    "enabled": true
                }
            ],
            "auth": null,
            "events": null,
            "folder": null,
            "protocolProfileBehavior": {
                "disableBodyPruning": true
            },
            "responses": [],
            "currentHelper": null,
            "helperAttributes": null,
            "collectionId": "8f2bb20361d41620f8385525cc5329e8",
            "rawModeData": ""
        },
        {
            "id": "4e160bdfad972bddc87c356e8ced6933",
            "name": "Complaint",
            "url": "httpapi.elasticemail.com\/mailer\/list\/complaint",
            "description": "This api will return you the list of email addresses which are currently in your block list. ",
            "data": [],
            "dataMode": "raw",
            "headerData": null,
            "method": "get",
            "pathVariableData": [],
            "queryParams": [
                {
                    "key": "api_key",
                    "description": "your api key",
                    "value": "",
                    "equals": true,
                    "enabled": true
                },
                {
                    "key": "username",
                    "description": "username",
                    "value": "",
                    "equals": true,
                    "enabled": true
                }
            ],
            "auth": null,
            "events": null,
            "folder": null,
            "protocolProfileBehavior": {
                "disableBodyPruning": true
            },
            "responses": [],
            "currentHelper": null,
            "helperAttributes": null,
            "collectionId": "8f2bb20361d41620f8385525cc5329e8",
            "rawModeData": ""
        },
        {
            "id": "4aa4721937f33c3d8e665c1c57caa002",
            "name": "Unsubscribed",
            "url": "httpapi.elasticemail.com\/mailer\/lists\/unsubscribed",
            "description": "This api will return you the list of email addresses which are currently in your block list. ",
            "data": [],
            "dataMode": "raw",
            "headerData": null,
            "method": "get",
            "pathVariableData": [],
            "queryParams": [
                {
                    "key": "api_key",
                    "description": "your api key",
                    "value": "",
                    "equals": true,
                    "enabled": true
                },
                {
                    "key": "username",
                    "description": "username",
                    "value": "",
                    "equals": true,
                    "enabled": true
                }
            ],
            "auth": null,
            "events": null,
            "folder": null,
            "protocolProfileBehavior": {
                "disableBodyPruning": true
            },
            "responses": [],
            "currentHelper": null,
            "helperAttributes": null,
            "collectionId": "8f2bb20361d41620f8385525cc5329e8",
            "rawModeData": ""
        },
        {
            "id": "22cdaf1199e0975f2a82629917847349",
            "name": "Send Email",
            "url": "httpapi.elasticemail.com\/mailer\/send\/",
            "description": "api.elasticemail.com",
            "data": [],
            "dataMode": "raw",
            "headerData": null,
            "method": "get",
            "pathVariableData": [],
            "queryParams": [
                {
                    "key": "api_key",
                    "description": "your api key",
                    "value": "",
                    "equals": true,
                    "enabled": true
                },
                {
                    "key": "body_html",
                    "description": "html email body",
                    "value": "",
                    "equals": true,
                    "enabled": true
                },
                {
                    "key": "body_text",
                    "description": "text email body",
                    "value": "",
                    "equals": true,
                    "enabled": true
                },
                {
                    "key": "channel",
                    "description": "an id field (max 60 chars) that can be used for reporting",
                    "value": "",
                    "equals": true,
                    "enabled": true
                },
                {
                    "key": "charset",
                    "description": "text value of encoding for example: iso-8859-1, windows-1251, utf-8, us-ascii, windows-1250",
                    "value": "",
                    "equals": true,
                    "enabled": true
                },
                {
                    "key": "encodingtype",
                    "description": "0 for None, 1 for Raw7Bit, 2 for Raw8Bit, 3 for QuotedPrintable, 4 for Base64 (Default), 5 for Uue  note that you can also provide the text version such as Raw7Bit for value 1. ",
                    "value": "",
                    "equals": true,
                    "enabled": true
                },
                {
                    "key": "from",
                    "description": "from email address",
                    "value": "",
                    "equals": true,
                    "enabled": true
                },
                {
                    "key": "from_name",
                    "description": "display name for from email address",
                    "value": "",
                    "equals": true,
                    "enabled": true
                },
                {
                    "key": "lists",
                    "description": "the name of a contact list you would like to send to. Separate multiple contact lists by commas",
                    "value": "",
                    "equals": true,
                    "enabled": true
                },
                {
                    "key": "merge_firstname",
                    "description": "if sending to a template you can send merge_ fields to merge data with the template. Template fields are entered with {firstname}, {lastname} etc.",
                    "value": "",
                    "equals": true,
                    "enabled": true
                },
                {
                    "key": "merge_lastname",
                    "description": "if sending to a template you can send merge_ fields to merge data with the template. Template fields are entered with {firstname}, {lastname} etc.",
                    "value": "",
                    "equals": true,
                    "enabled": true
                },
                {
                    "key": "reply_to",
                    "description": "email address to reply to",
                    "value": "",
                    "equals": true,
                    "enabled": true
                },
                {
                    "key": "reply_to_name",
                    "description": "display name of the reply to address",
                    "value": "",
                    "equals": true,
                    "enabled": true
                },
                {
                    "key": "sender",
                    "description": "email address of the sender",
                    "value": "",
                    "equals": true,
                    "enabled": true
                },
                {
                    "key": "sender_name",
                    "description": "display name sender ",
                    "value": "",
                    "equals": true,
                    "enabled": true
                },
                {
                    "key": "subject",
                    "description": "email subject ",
                    "value": "",
                    "equals": true,
                    "enabled": true
                },
                {
                    "key": "template",
                    "description": "the name of an email template you have created in your account. If you send a template",
                    "value": "",
                    "equals": true,
                    "enabled": true
                },
                {
                    "key": "time_offset_minutes",
                    "description": "number of minutes in the future this email should be sent ",
                    "value": "",
                    "equals": true,
                    "enabled": true
                },
                {
                    "key": "total",
                    "description": "semi colon separated list of email recipients (each email is treated separately, like a BCC)",
                    "value": "",
                    "equals": true,
                    "enabled": true
                },
                {
                    "key": "username",
                    "description": "username",
                    "value": "",
                    "equals": true,
                    "enabled": true
                }
            ],
            "auth": null,
            "events": null,
            "folder": null,
            "protocolProfileBehavior": {
                "disableBodyPruning": true
            },
            "responses": [],
            "currentHelper": null,
            "helperAttributes": null,
            "collectionId": "8f2bb20361d41620f8385525cc5329e8",
            "rawModeData": ""
        },
        {
            "id": "afa81384b42e3628fdd7a410235f585a",
            "name": "Log Activity",
            "url": "httpapi.elasticemail.com\/mailer\/status\/log",
            "description": "The detailed activity log api allows you to get detailed information from your activity log on the emails that you have sent. Information can be narrowed by email status, channel and datetime.",
            "data": [],
            "dataMode": "raw",
            "headerData": null,
            "method": "get",
            "pathVariableData": [],
            "queryParams": [
                {
                    "key": "api_key",
                    "description": "your api key",
                    "value": "",
                    "equals": true,
                    "enabled": true
                },
                {
                    "key": "channel",
                    "description": "an id field (max 60 chars) that can be used for reporting",
                    "value": "",
                    "equals": true,
                    "enabled": true
                },
                {
                    "key": "compress",
                    "description": "True if you want the results returned as a compressed zip file",
                    "value": "",
                    "equals": true,
                    "enabled": true
                },
                {
                    "key": "format",
                    "description": "csv or xml",
                    "value": "",
                    "equals": true,
                    "enabled": true
                },
                {
                    "key": "from",
                    "description": "from email address",
                    "value": "",
                    "equals": true,
                    "enabled": true
                },
                {
                    "key": "status",
                    "description": "One of the following status values: 0 or all, 1 for ReadyToSend, 2 for InProgress, 4 for Bounced, 5 for Sent, 6 for Opened, 7 for Clicked, 8 for Unsubscribed, 9 for Abuse Report",
                    "value": "",
                    "equals": true,
                    "enabled": true
                },
                {
                    "key": "to",
                    "description": "Server time in the format: 5\/19\/2011 10:54:20 PM",
                    "value": "",
                    "equals": true,
                    "enabled": true
                },
                {
                    "key": "username",
                    "description": "username",
                    "value": "",
                    "equals": true,
                    "enabled": true
                }
            ],
            "auth": null,
            "events": null,
            "folder": null,
            "protocolProfileBehavior": {
                "disableBodyPruning": true
            },
            "responses": [],
            "currentHelper": null,
            "helperAttributes": null,
            "collectionId": "8f2bb20361d41620f8385525cc5329e8",
            "rawModeData": ""
        },
        {
            "id": "42990f24c71871a605265f586bb6a4f0",
            "name": "Get Status",
            "url": "httpapi.elasticemail.com\/mailer\/status\/{message_id}",
            "description": "Get the status of an email message",
            "data": [],
            "dataMode": "raw",
            "headerData": null,
            "method": "get",
            "pathVariableData": [],
            "queryParams": [
                {
                    "key": "api_key",
                    "description": "your api key",
                    "value": "",
                    "equals": true,
                    "enabled": true
                },
                {
                    "key": "message_id",
                    "description": "The ID of the email message.",
                    "value": "",
                    "equals": true,
                    "enabled": true
                },
                {
                    "key": "showdelivered",
                    "description": "true - This will return all the recipients who succeeded. ",
                    "value": "",
                    "equals": true,
                    "enabled": true
                },
                {
                    "key": "showdetails",
                    "description": "true  - This will return all recipients for each status.",
                    "value": "",
                    "equals": true,
                    "enabled": true
                },
                {
                    "key": "showerrors",
                    "description": "true - This will return all the recipients who bounced with details on why",
                    "value": "",
                    "equals": true,
                    "enabled": true
                },
                {
                    "key": "showfailed",
                    "description": "true - This will return all the recipients who bounced. ",
                    "value": "",
                    "equals": true,
                    "enabled": true
                },
                {
                    "key": "showpending",
                    "description": "true - This will return all the recipients still in progress. ",
                    "value": "",
                    "equals": true,
                    "enabled": true
                },
                {
                    "key": "showstats",
                    "description": "Show stats.",
                    "value": "",
                    "equals": true,
                    "enabled": true
                },
                {
                    "key": "username",
                    "description": "username",
                    "value": "",
                    "equals": true,
                    "enabled": true
                }
            ],
            "auth": null,
            "events": null,
            "folder": null,
            "protocolProfileBehavior": {
                "disableBodyPruning": true
            },
            "responses": [],
            "currentHelper": null,
            "helperAttributes": null,
            "collectionId": "8f2bb20361d41620f8385525cc5329e8",
            "rawModeData": ""
        }
    ]
}